[
  {
    "title": "揭秘58同城维修“幽灵订单”",
    "url": "https://cn.bing.com/search?q=%e6%8f%ad%e7%a7%9858%e5%90%8c%e5%9f%8e%e7%bb%b4%e4%bf%ae%e2%80%9c%e5%b9%bd%e7%81%b5%e8%ae%a2%e5%8d%95%e2%80%9d&efirst=0&ecount=50&filters=tnTID%3a%22DSBOS_52D26116742E4828BFE50963A991E1AA%22+tnVersion%3a%223f4ab66eed784ed0ad52ef1e8b1b6e16%22+Segment%3a%22popularnow.carousel%22+tnCol%3a%220%22+tnOrder%3a%226e03ddda-fbe0-4c33-88a2-9ca4a54345d9%22&form=HPNN01",
    "image": "https://cn.bing.com/th?id=ONUT.knRwdKE28_v0n6Pt4Xhx-Q&w=186&h=88&c=7&rs=2&qlt=80&pid=PopNow"
  },
  {
    "title": "王大陆及其女友获刑6个月",
    "url": "https://cn.bing.com/search?q=%e7%8e%8b%e5%a4%a7%e9%99%86%e5%8f%8a%e5%85%b6%e5%a5%b3%e5%8f%8b%e8%8e%b7%e5%88%916%e4%b8%aa%e6%9c%88&efirst=0&ecount=50&filters=tnTID%3a%22DSBOS_78A27651D1F44430BE0319DA7A0EE26D%22+tnVersion%3a%223f4ab66eed784ed0ad52ef1e8b1b6e16%22+Segment%3a%22popularnow.carousel%22+tnCol%3a%221%22+tnOrder%3a%226e03ddda-fbe0-4c33-88a2-9ca4a54345d9%22&form=HPNN01",
    "image": "https://cn.bing.com/th?id=ONUT.Hxp5EvycI3Yg8IrH564Ocw&w=186&h=88&c=7&rs=2&qlt=80&pid=PopNow"
  },
  {
    "title": "宁德时代新电池续航1500km",
    "url": "https://cn.bing.com/search?q=%e5%ae%81%e5%be%b7%e6%97%b6%e4%bb%a3%e6%96%b0%e7%94%b5%e6%b1%a0%e7%bb%ad%e8%88%aa1500km&efirst=0&ecount=50&filters=tnTID%3a%22DSBOS_246A20E2BA84464F91B72CD33517B041%22+tnVersion%3a%223f4ab66eed784ed0ad52ef1e8b1b6e16%22+Segment%3a%22popularnow.carousel%22+tnCol%3a%222%22+tnOrder%3a%226e03ddda-fbe0-4c33-88a2-9ca4a54345d9%22&form=HPNN01",
    "image": "https://cn.bing.com/th?id=ONUT.CBiIZ0JJwmpsLxEkUi18bw&w=186&h=88&c=7&rs=2&qlt=80&pid=PopNow"
  },
  {
    "title": "马斯克600亿美元锁定Cursor",
    "url": "https://cn.bing.com/search?q=%e9%a9%ac%e6%96%af%e5%85%8b600%e4%ba%bf%e7%be%8e%e5%85%83%e9%94%81%e5%ae%9aCursor&efirst=0&ecount=50&filters=tnTID%3a%22DSBOS_B57FD949D64541479987E18936E6DA43%22+tnVersion%3a%223f4ab66eed784ed0ad52ef1e8b1b6e16%22+Segment%3a%22popularnow.carousel%22+tnCol%3a%223%22+tnOrder%3a%226e03ddda-fbe0-4c33-88a2-9ca4a54345d9%22&form=HPNN01",
    "image": "https://cn.bing.com/th?id=ONUT.2oQRqmRlb60Gf-Croln_EQ&w=186&h=88&c=7&rs=2&qlt=80&pid=PopNow"
  },
  {
    "title": "男子心脏停跳2天后生还",
    "url": "https://cn.bing.com/search?q=%e7%94%b7%e5%ad%90%e5%bf%83%e8%84%8f%e5%81%9c%e8%b7%b32%e5%a4%a9%e5%90%8e%e7%94%9f%e8%bf%98&efirst=0&ecount=50&filters=tnTID%3a%22DSBOS_BFE96115952A467DA92AEF5235D43EC8%22+tnVersion%3a%223f4ab66eed784ed0ad52ef1e8b1b6e16%22+Segment%3a%22popularnow.carousel%22+tnCol%3a%224%22+tnOrder%3a%226e03ddda-fbe0-4c33-88a2-9ca4a54345d9%22&form=HPNN01",
    "image": "https://cn.bing.com/th?id=ONUT.WUo44UaFiNHQ16M34Cm4Sg&w=186&h=88&c=7&rs=2&qlt=80&pid=PopNow"
  },
  {
    "title": "“豪华卧铺大巴”违规改装",
    "url": "https://cn.bing.com/search?q=%e2%80%9c%e8%b1%aa%e5%8d%8e%e5%8d%a7%e9%93%ba%e5%a4%a7%e5%b7%b4%e2%80%9d%e8%bf%9d%e8%a7%84%e6%94%b9%e8%a3%85&efirst=0&ecount=50&filters=tnTID%3a%22DSBOS_DCD7DD6BA34B4BF2B5EE156B41D01104%22+tnVersion%3a%223f4ab66eed784ed0ad52ef1e8b1b6e16%22+Segment%3a%22popularnow.carousel%22+tnCol%3a%225%22+tnOrder%3a%226e03ddda-fbe0-4c33-88a2-9ca4a54345d9%22&form=HPNN01",
    "image": "https://cn.bing.com/th?id=ONUT.GHOVyzCbmBRcOFCo-uMF4g&w=186&h=88&c=7&rs=2&qlt=80&pid=PopNow"
  },
  {
    "title": "肯德基门店回应酱料收费",
    "url": "https://cn.bing.com/search?q=%e8%82%af%e5%be%b7%e5%9f%ba%e9%97%a8%e5%ba%97%e5%9b%9e%e5%ba%94%e9%85%b1%e6%96%99%e6%94%b6%e8%b4%b9&efirst=0&ecount=50&filters=tnTID%3a%22DSBOS_4A9F6296ECD04FDF83DEE22ACBE58F41%22+tnVersion%3a%223f4ab66eed784ed0ad52ef1e8b1b6e16%22+Segment%3a%22popularnow.carousel%22+tnCol%3a%226%22+tnOrder%3a%226e03ddda-fbe0-4c33-88a2-9ca4a54345d9%22&form=HPNN01",
    "image": "https://cn.bing.com/th?id=OIP.QXZN0HwJNlOUCekdvSV5iAHaF1&w=186&h=88&c=7&rs=2&qlt=80&pid=PopNow"
  },
  {
    "title": "格力海信铜铝之争正面开火",
    "url": "https://cn.bing.com/search?q=%e6%a0%bc%e5%8a%9b%e6%b5%b7%e4%bf%a1%e9%93%9c%e9%93%9d%e4%b9%8b%e4%ba%89%e6%ad%a3%e9%9d%a2%e5%bc%80%e7%81%ab&efirst=0&ecount=50&filters=tnTID%3a%22DSBOS_0B8DB1CF54E2403D829AE9A049CBA4F7%22+tnVersion%3a%223f4ab66eed784ed0ad52ef1e8b1b6e16%22+Segment%3a%22popularnow.carousel%22+tnCol%3a%227%22+tnOrder%3a%226e03ddda-fbe0-4c33-88a2-9ca4a54345d9%22&form=HPNN01",
    "image": "https://cn.bing.com/th?id=ONUT.MUTO8jAewtR0h3tYnwsd6A&w=186&h=88&c=7&rs=2&qlt=80&pid=PopNow"
  },
  {
    "title": "苹果或被印度罚380亿美元",
    "url": "https://cn.bing.com/search?q=%e8%8b%b9%e6%9e%9c%e6%88%96%e8%a2%ab%e5%8d%b0%e5%ba%a6%e7%bd%9a380%e4%ba%bf%e7%be%8e%e5%85%83&efirst=0&ecount=50&filters=tnTID%3a%22DSBOS_748579EFA4C748A99A01B6C009A19585%22+tnVersion%3a%223f4ab66eed784ed0ad52ef1e8b1b6e16%22+Segment%3a%22popularnow.carousel%22+tnCol%3a%228%22+tnOrder%3a%226e03ddda-fbe0-4c33-88a2-9ca4a54345d9%22&form=HPNN01",
    "image": "https://cn.bing.com/th?id=ONUT.pKcolzr-yHe7HvzybtdK5g&w=186&h=88&c=7&rs=2&qlt=80&pid=PopNow"
  },
  {
    "title": "哪吒造车烧钱183亿",
    "url": "https://cn.bing.com/search?q=%e5%93%aa%e5%90%92%e9%80%a0%e8%bd%a6%e7%83%a7%e9%92%b1183%e4%ba%bf&efirst=0&ecount=50&filters=tnTID%3a%22DSBOS_A91EA62567F74149A1997D485AAC18D3%22+tnVersion%3a%223f4ab66eed784ed0ad52ef1e8b1b6e16%22+Segment%3a%22popularnow.carousel%22+tnCol%3a%229%22+tnOrder%3a%226e03ddda-fbe0-4c33-88a2-9ca4a54345d9%22&form=HPNN01",
    "image": "https://cn.bing.com/th?id=ONUT.FyTxspo31s3mpJcTcqe7lg&w=186&h=88&c=7&rs=2&qlt=80&pid=PopNow"
  },
  {
    "title": "电影《灵魂摆渡》全AI生成",
    "url": "https://cn.bing.com/search?q=%e7%94%b5%e5%bd%b1%e3%80%8a%e7%81%b5%e9%ad%82%e6%91%86%e6%b8%a1%e3%80%8b%e5%85%a8AI%e7%94%9f%e6%88%90&efirst=0&ecount=50&filters=tnTID%3a%22DSBOS_724CB01FBF174EF59A15C62D4DA56757%22+tnVersion%3a%223f4ab66eed784ed0ad52ef1e8b1b6e16%22+Segment%3a%22popularnow.carousel%22+tnCol%3a%2210%22+tnOrder%3a%226e03ddda-fbe0-4c33-88a2-9ca4a54345d9%22&form=HPNN01",
    "image": "https://cn.bing.com/th?id=ONUT.nhuEpKQ7wSMi4Sk6qyi1ZQ&w=186&h=88&c=7&rs=2&qlt=80&pid=PopNow"
  },
  {
    "title": "11人野外吃蘑菇中毒",
    "url": "https://cn.bing.com/search?q=11%e4%ba%ba%e9%87%8e%e5%a4%96%e5%90%83%e8%98%91%e8%8f%87%e4%b8%ad%e6%af%92&efirst=0&ecount=50&filters=tnTID%3a%22DSBOS_584823CA5B88458B994701AD3191E0A2%22+tnVersion%3a%223f4ab66eed784ed0ad52ef1e8b1b6e16%22+Segment%3a%22popularnow.carousel%22+tnCol%3a%2211%22+tnOrder%3a%226e03ddda-fbe0-4c33-88a2-9ca4a54345d9%22&form=HPNN01",
    "image": "https://cn.bing.com/th?id=ONUT.13tLrgLNkvX89i1bqNlrhw&w=186&h=88&c=7&rs=2&qlt=80&pid=PopNow"
  },
  {
    "title": "微信宣布5国可用微信支付",
    "url": "https://cn.bing.com/search?q=%e5%be%ae%e4%bf%a1%e5%ae%a3%e5%b8%835%e5%9b%bd%e5%8f%af%e7%94%a8%e5%be%ae%e4%bf%a1%e6%94%af%e4%bb%98&efirst=0&ecount=50&filters=tnTID%3a%22DSBOS_26E3E9F7AB474D59BD1FB7012064672B%22+tnVersion%3a%223f4ab66eed784ed0ad52ef1e8b1b6e16%22+Segment%3a%22popularnow.carousel%22+tnCol%3a%2212%22+tnOrder%3a%226e03ddda-fbe0-4c33-88a2-9ca4a54345d9%22&form=HPNN01",
    "image": "https://cn.bing.com/th?id=ONUT.W47Cu8XA7RBN1g_G9ltdkg&w=186&h=88&c=7&rs=2&qlt=80&pid=PopNow"
  },
  {
    "title": "民宿藏多个针孔摄像头直播",
    "url": "https://cn.bing.com/search?q=%e6%b0%91%e5%ae%bf%e8%97%8f%e5%a4%9a%e4%b8%aa%e9%92%88%e5%ad%94%e6%91%84%e5%83%8f%e5%a4%b4%e7%9b%b4%e6%92%ad&efirst=0&ecount=50&filters=tnTID%3a%22DSBOS_75065FF15EC34113A62C7E67A95B6C0D%22+tnVersion%3a%223f4ab66eed784ed0ad52ef1e8b1b6e16%22+Segment%3a%22popularnow.carousel%22+tnCol%3a%2213%22+tnOrder%3a%226e03ddda-fbe0-4c33-88a2-9ca4a54345d9%22&form=HPNN01",
    "image": "https://cn.bing.com/th?id=ONUT.ccbnpKE2f5l5R3R5yY_cgA&w=186&h=88&c=7&rs=2&qlt=80&pid=PopNow"
  },
  {
    "title": "幼儿园上午缴费下午闭园",
    "url": "https://cn.bing.com/search?q=%e5%b9%bc%e5%84%bf%e5%9b%ad%e4%b8%8a%e5%8d%88%e7%bc%b4%e8%b4%b9%e4%b8%8b%e5%8d%88%e9%97%ad%e5%9b%ad&efirst=0&ecount=50&filters=tnTID%3a%22DSBOS_1063D094EF714E4B87162764A090D046%22+tnVersion%3a%223f4ab66eed784ed0ad52ef1e8b1b6e16%22+Segment%3a%22popularnow.carousel%22+tnCol%3a%2214%22+tnOrder%3a%226e03ddda-fbe0-4c33-88a2-9ca4a54345d9%22&form=HPNN01",
    "image": "https://cn.bing.com/th?id=ONUT.oBlx3A7L5DdMhTCYOvHqpg&w=186&h=88&c=7&rs=2&qlt=80&pid=PopNow"
  },
  {
    "title": "大连一麦当劳店禁止化妆",
    "url": "https://cn.bing.com/search?q=%e5%a4%a7%e8%bf%9e%e4%b8%80%e9%ba%a6%e5%bd%93%e5%8a%b3%e5%ba%97%e7%a6%81%e6%ad%a2%e5%8c%96%e5%a6%86&efirst=0&ecount=50&filters=tnTID%3a%22DSBOS_B984D55FF12C4F8D9AF81F758534942F%22+tnVersion%3a%223f4ab66eed784ed0ad52ef1e8b1b6e16%22+Segment%3a%22popularnow.carousel%22+tnCol%3a%2215%22+tnOrder%3a%226e03ddda-fbe0-4c33-88a2-9ca4a54345d9%22&form=HPNN01",
    "image": "https://cn.bing.com/th?id=ONUT.JuipfcDHnUg2887roHUNWA&w=186&h=88&c=7&rs=2&qlt=80&pid=PopNow"
  },
  {
    "title": "油价下降加满少22元",
    "url": "https://cn.bing.com/search?q=%e6%b2%b9%e4%bb%b7%e4%b8%8b%e9%99%8d%e5%8a%a0%e6%bb%a1%e5%b0%9122%e5%85%83&efirst=0&ecount=50&filters=tnTID%3a%22DSBOS_550F7CF99A874CB4A415DCFDB6FC91E5%22+tnVersion%3a%223f4ab66eed784ed0ad52ef1e8b1b6e16%22+Segment%3a%22popularnow.carousel%22+tnCol%3a%2216%22+tnOrder%3a%226e03ddda-fbe0-4c33-88a2-9ca4a54345d9%22&form=HPNN01",
    "image": "https://cn.bing.com/th?id=ONUT.UNoWifVbO5UXYjLttNKvBw&w=186&h=88&c=7&rs=2&qlt=80&pid=PopNow"
  },
  {
    "title": "首例职场性侵工伤认定案开庭",
    "url": "https://cn.bing.com/search?q=%e9%a6%96%e4%be%8b%e8%81%8c%e5%9c%ba%e6%80%a7%e4%be%b5%e5%b7%a5%e4%bc%a4%e8%ae%a4%e5%ae%9a%e6%a1%88%e5%bc%80%e5%ba%ad&efirst=0&ecount=50&filters=tnTID%3a%22DSBOS_7FC9D29B1EA64AF5945C11E70EA671F2%22+tnVersion%3a%223f4ab66eed784ed0ad52ef1e8b1b6e16%22+Segment%3a%22popularnow.carousel%22+tnCol%3a%2217%22+tnOrder%3a%226e03ddda-fbe0-4c33-88a2-9ca4a54345d9%22&form=HPNN01",
    "image": "https://cn.bing.com/th?id=ONUT.8bjDEvNSg2ufi5IK7pUZbw&w=186&h=88&c=7&rs=2&qlt=80&pid=PopNow"
  },
  {
    "title": "员工把学生营养午餐带回家",
    "url": "https://cn.bing.com/search?q=%e5%91%98%e5%b7%a5%e6%8a%8a%e5%ad%a6%e7%94%9f%e8%90%a5%e5%85%bb%e5%8d%88%e9%a4%90%e5%b8%a6%e5%9b%9e%e5%ae%b6&efirst=0&ecount=50&filters=tnTID%3a%22DSBOS_8081421427D74F62A93E70A06FCE6C63%22+tnVersion%3a%223f4ab66eed784ed0ad52ef1e8b1b6e16%22+Segment%3a%22popularnow.carousel%22+tnCol%3a%2218%22+tnOrder%3a%226e03ddda-fbe0-4c33-88a2-9ca4a54345d9%22&form=HPNN01",
    "image": "https://cn.bing.com/th?id=OIP.UdFfl88gB-E3XJWupzYFGQHaE8&w=186&h=88&c=7&rs=2&qlt=80&pid=PopNow"
  },
  {
    "title": "国安部披露AI投毒手段",
    "url": "https://cn.bing.com/search?q=%e5%9b%bd%e5%ae%89%e9%83%a8%e6%8a%ab%e9%9c%b2AI%e6%8a%95%e6%af%92%e6%89%8b%e6%ae%b5&efirst=0&ecount=50&filters=tnTID%3a%22DSBOS_489C90D33BB84AFCBB0D4C90258E2952%22+tnVersion%3a%223f4ab66eed784ed0ad52ef1e8b1b6e16%22+Segment%3a%22popularnow.carousel%22+tnCol%3a%2219%22+tnOrder%3a%226e03ddda-fbe0-4c33-88a2-9ca4a54345d9%22&form=HPNN01",
    "image": "https://cn.bing.com/th?id=ONUT.6Dx3YIfZp3eDrZUx08C6fw&w=186&h=88&c=7&rs=2&qlt=80&pid=PopNow"
  }
]