[
  {
    "title": "习近平会见印度总理莫迪",
    "hot": "22285897",
    "url": "https://www.toutiao.com/article/7544595891982713395",
    "time": ""
  },
  {
    "title": "普京抵达天津出席上合峰会",
    "hot": "20165114",
    "url": "https://www.toutiao.com/trending/7544311831238672426/?category_name=topic_innerflow&event_type=hot_board&log_pb=%7B%22category_name%22%3A%22topic_innerflow%22%2C%22cluster_type%22%3A%222%22%2C%22enter_from%22%3A%22click_category%22%2C%22entrance_hotspot%22%3A%22outside%22%2C%22event_type%22%3A%22hot_board%22%2C%22hot_board_cluster_id%22%3A%227544311831238672426%22%2C%22hot_board_impr_id%22%3A%22202508311237275FA1DF6103E3A21E3F6D%22%2C%22jump_page%22%3A%22hot_board_page%22%2C%22location%22%3A%22news_hot_card%22%2C%22page_location%22%3A%22hot_board_page%22%2C%22source%22%3A%22trending_tab%22%2C%22style_id%22%3A%2240132%22%2C%22title%22%3A%22%E6%99%AE%E4%BA%AC%E6%8A%B5%E8%BE%BE%E5%A4%A9%E6%B4%A5%E5%87%BA%E5%B8%AD%E4%B8%8A%E5%90%88%E5%B3%B0%E4%BC%9A%22%7D&rank=&style_id=40132&topic_id=7544311831238672426",
    "time": ""
  },
  {
    "title": "“桥”见上合天津峰会 欢迎八方来客",
    "hot": "18246149",
    "url": "https://www.toutiao.com/article/7544361135655371310",
    "time": ""
  },
  {
    "title": "牛弹琴：特朗普真气坏了",
    "hot": "16509799",
    "url": "https://www.toutiao.com/trending/7544531253106576906/?category_name=topic_innerflow&event_type=hot_board&log_pb=%7B%22category_name%22%3A%22topic_innerflow%22%2C%22cluster_type%22%3A%2213%22%2C%22enter_from%22%3A%22click_category%22%2C%22entrance_hotspot%22%3A%22outside%22%2C%22event_type%22%3A%22hot_board%22%2C%22hot_board_cluster_id%22%3A%227544531253106576906%22%2C%22hot_board_impr_id%22%3A%22202508311237275FA1DF6103E3A21E3F6D%22%2C%22jump_page%22%3A%22hot_board_page%22%2C%22location%22%3A%22news_hot_card%22%2C%22page_location%22%3A%22hot_board_page%22%2C%22source%22%3A%22trending_tab%22%2C%22style_id%22%3A%2240132%22%2C%22title%22%3A%22%E7%89%9B%E5%BC%B9%E7%90%B4%EF%BC%9A%E7%89%B9%E6%9C%97%E6%99%AE%E7%9C%9F%E6%B0%94%E5%9D%8F%E4%BA%86%22%7D&rank=&style_id=40132&topic_id=7544531253106576906",
    "time": ""
  },
  {
    "title": "土耳其总统埃尔多安抵达天津",
    "hot": "14938684",
    "url": "https://www.toutiao.com/trending/7544451728248782858/?category_name=topic_innerflow&event_type=hot_board&log_pb=%7B%22category_name%22%3A%22topic_innerflow%22%2C%22cluster_type%22%3A%223%22%2C%22enter_from%22%3A%22click_category%22%2C%22entrance_hotspot%22%3A%22outside%22%2C%22event_type%22%3A%22hot_board%22%2C%22hot_board_cluster_id%22%3A%227544451728248782858%22%2C%22hot_board_impr_id%22%3A%22202508311237275FA1DF6103E3A21E3F6D%22%2C%22jump_page%22%3A%22hot_board_page%22%2C%22location%22%3A%22news_hot_card%22%2C%22page_location%22%3A%22hot_board_page%22%2C%22source%22%3A%22trending_tab%22%2C%22style_id%22%3A%2240132%22%2C%22title%22%3A%22%E5%9C%9F%E8%80%B3%E5%85%B6%E6%80%BB%E7%BB%9F%E5%9F%83%E5%B0%94%E5%A4%9A%E5%AE%89%E6%8A%B5%E8%BE%BE%E5%A4%A9%E6%B4%A5%22%7D&rank=&style_id=40132&topic_id=7544451728248782858",
    "time": ""
  },
  {
    "title": "网警来送“网络安全课”了",
    "hot": "13517080",
    "url": "https://www.toutiao.com/trending/7544208474658816041/?category_name=topic_innerflow&event_type=hot_board&log_pb=%7B%22category_name%22%3A%22topic_innerflow%22%2C%22cluster_type%22%3A%222%22%2C%22enter_from%22%3A%22click_category%22%2C%22entrance_hotspot%22%3A%22outside%22%2C%22event_type%22%3A%22hot_board%22%2C%22hot_board_cluster_id%22%3A%227544208474658816041%22%2C%22hot_board_impr_id%22%3A%22202508311237275FA1DF6103E3A21E3F6D%22%2C%22jump_page%22%3A%22hot_board_page%22%2C%22location%22%3A%22news_hot_card%22%2C%22page_location%22%3A%22hot_board_page%22%2C%22source%22%3A%22trending_tab%22%2C%22style_id%22%3A%2240132%22%2C%22title%22%3A%22%E7%BD%91%E8%AD%A6%E6%9D%A5%E9%80%81%E2%80%9C%E7%BD%91%E7%BB%9C%E5%AE%89%E5%85%A8%E8%AF%BE%E2%80%9D%E4%BA%86%22%7D&rank=&style_id=40132&topic_id=7544208474658816041",
    "time": ""
  },
  {
    "title": "学者：胡塞高层团灭 一把手行踪成谜",
    "hot": "12230760",
    "url": "https://www.toutiao.com/trending/7544551699063508526/?category_name=topic_innerflow&event_type=hot_board&log_pb=%7B%22category_name%22%3A%22topic_innerflow%22%2C%22cluster_type%22%3A%2213%22%2C%22enter_from%22%3A%22click_category%22%2C%22entrance_hotspot%22%3A%22outside%22%2C%22event_type%22%3A%22hot_board%22%2C%22hot_board_cluster_id%22%3A%227544551699063508526%22%2C%22hot_board_impr_id%22%3A%22202508311237275FA1DF6103E3A21E3F6D%22%2C%22jump_page%22%3A%22hot_board_page%22%2C%22location%22%3A%22news_hot_card%22%2C%22page_location%22%3A%22hot_board_page%22%2C%22source%22%3A%22trending_tab%22%2C%22style_id%22%3A%2240132%22%2C%22title%22%3A%22%E5%AD%A6%E8%80%85%EF%BC%9A%E8%83%A1%E5%A1%9E%E9%AB%98%E5%B1%82%E5%9B%A2%E7%81%AD+%E4%B8%80%E6%8A%8A%E6%89%8B%E8%A1%8C%E8%B8%AA%E6%88%90%E8%B0%9C%22%7D&rank=&style_id=40132&topic_id=7544551699063508526",
    "time": ""
  },
  {
    "title": "如何看待莫迪在中国与泽连斯基通话",
    "hot": "11066849",
    "url": "https://www.toutiao.com/trending/7543802263295311935/?category_name=topic_innerflow&event_type=hot_board&log_pb=%7B%22category_name%22%3A%22topic_innerflow%22%2C%22cluster_type%22%3A%220%22%2C%22enter_from%22%3A%22click_category%22%2C%22entrance_hotspot%22%3A%22outside%22%2C%22event_type%22%3A%22hot_board%22%2C%22hot_board_cluster_id%22%3A%227543802263295311935%22%2C%22hot_board_impr_id%22%3A%22202508311237275FA1DF6103E3A21E3F6D%22%2C%22jump_page%22%3A%22hot_board_page%22%2C%22location%22%3A%22news_hot_card%22%2C%22page_location%22%3A%22hot_board_page%22%2C%22source%22%3A%22trending_tab%22%2C%22style_id%22%3A%2240132%22%2C%22title%22%3A%22%E5%A6%82%E4%BD%95%E7%9C%8B%E5%BE%85%E8%8E%AB%E8%BF%AA%E5%9C%A8%E4%B8%AD%E5%9B%BD%E4%B8%8E%E6%B3%BD%E8%BF%9E%E6%96%AF%E5%9F%BA%E9%80%9A%E8%AF%9D%22%7D&rank=&style_id=40132&topic_id=7543802263295311935",
    "time": ""
  },
  {
    "title": "一图看懂中国航天追梦之路",
    "hot": "10013699",
    "url": "https://www.toutiao.com/trending/7544538794164207635/?category_name=topic_innerflow&event_type=hot_board&log_pb=%7B%22category_name%22%3A%22topic_innerflow%22%2C%22cluster_type%22%3A%222%22%2C%22enter_from%22%3A%22click_category%22%2C%22entrance_hotspot%22%3A%22outside%22%2C%22event_type%22%3A%22hot_board%22%2C%22hot_board_cluster_id%22%3A%227544538794164207635%22%2C%22hot_board_impr_id%22%3A%22202508311237275FA1DF6103E3A21E3F6D%22%2C%22jump_page%22%3A%22hot_board_page%22%2C%22location%22%3A%22news_hot_card%22%2C%22page_location%22%3A%22hot_board_page%22%2C%22source%22%3A%22trending_tab%22%2C%22style_id%22%3A%2240132%22%2C%22title%22%3A%22%E4%B8%80%E5%9B%BE%E7%9C%8B%E6%87%82%E4%B8%AD%E5%9B%BD%E8%88%AA%E5%A4%A9%E8%BF%BD%E6%A2%A6%E4%B9%8B%E8%B7%AF%22%7D&rank=&style_id=40132&topic_id=7544538794164207635",
    "time": ""
  },
  {
    "title": "9月起大额存款利息收20%个税？谣言",
    "hot": "9060769",
    "url": "https://www.toutiao.com/trending/7543794416478797870/?category_name=topic_innerflow&event_type=hot_board&log_pb=%7B%22category_name%22%3A%22topic_innerflow%22%2C%22cluster_type%22%3A%228%22%2C%22enter_from%22%3A%22click_category%22%2C%22entrance_hotspot%22%3A%22outside%22%2C%22event_type%22%3A%22hot_board%22%2C%22hot_board_cluster_id%22%3A%227543794416478797870%22%2C%22hot_board_impr_id%22%3A%22202508311237275FA1DF6103E3A21E3F6D%22%2C%22jump_page%22%3A%22hot_board_page%22%2C%22location%22%3A%22news_hot_card%22%2C%22page_location%22%3A%22hot_board_page%22%2C%22source%22%3A%22trending_tab%22%2C%22style_id%22%3A%2240132%22%2C%22title%22%3A%229%E6%9C%88%E8%B5%B7%E5%A4%A7%E9%A2%9D%E5%AD%98%E6%AC%BE%E5%88%A9%E6%81%AF%E6%94%B620%25%E4%B8%AA%E7%A8%8E%EF%BC%9F%E8%B0%A3%E8%A8%80%22%7D&rank=&style_id=40132&topic_id=7543794416478797870",
    "time": ""
  }
]