[
  {
    "title": "多家银行下调部分存款挂牌利率",
    "hot": "29789985",
    "url": "https://www.toutiao.com/trending/7623785096319746084/?category_name=topic_innerflow&event_type=hot_board&log_pb=%7B%22category_name%22%3A%22topic_innerflow%22%2C%22cluster_type%22%3A%2210%22%2C%22enter_from%22%3A%22click_category%22%2C%22entrance_hotspot%22%3A%22outside%22%2C%22event_type%22%3A%22hot_board%22%2C%22hot_board_cluster_id%22%3A%227623785096319746084%22%2C%22hot_board_impr_id%22%3A%222026040213525126322A75551B0053726F%22%2C%22jump_page%22%3A%22hot_board_page%22%2C%22location%22%3A%22news_hot_card%22%2C%22page_location%22%3A%22hot_board_page%22%2C%22source%22%3A%22trending_tab%22%2C%22style_id%22%3A%2240132%22%2C%22title%22%3A%22%E5%A4%9A%E5%AE%B6%E9%93%B6%E8%A1%8C%E4%B8%8B%E8%B0%83%E9%83%A8%E5%88%86%E5%AD%98%E6%AC%BE%E6%8C%82%E7%89%8C%E5%88%A9%E7%8E%87%22%7D&rank=&style_id=40132&topic_id=7623785096319746084",
    "time": ""
  },
  {
    "title": "洪秀柱谈郑丽文访陆 提出三点期许",
    "hot": "26955093",
    "url": "https://www.toutiao.com/trending/7624008416050269734/?category_name=topic_innerflow&event_type=hot_board&log_pb=%7B%22category_name%22%3A%22topic_innerflow%22%2C%22cluster_type%22%3A%221%22%2C%22enter_from%22%3A%22click_category%22%2C%22entrance_hotspot%22%3A%22outside%22%2C%22event_type%22%3A%22hot_board%22%2C%22hot_board_cluster_id%22%3A%227624008416050269734%22%2C%22hot_board_impr_id%22%3A%222026040213525126322A75551B0053726F%22%2C%22jump_page%22%3A%22hot_board_page%22%2C%22location%22%3A%22news_hot_card%22%2C%22page_location%22%3A%22hot_board_page%22%2C%22source%22%3A%22trending_tab%22%2C%22style_id%22%3A%2240132%22%2C%22title%22%3A%22%E6%B4%AA%E7%A7%80%E6%9F%B1%E8%B0%88%E9%83%91%E4%B8%BD%E6%96%87%E8%AE%BF%E9%99%86+%E6%8F%90%E5%87%BA%E4%B8%89%E7%82%B9%E6%9C%9F%E8%AE%B8%22%7D&rank=&style_id=40132&topic_id=7624008416050269734",
    "time": ""
  },
  {
    "title": "脑机接口加速落地",
    "hot": "24389976",
    "url": "https://www.toutiao.com/article/7623698176617022004",
    "time": ""
  },
  {
    "title": "县委书记“六秒致辞”火了",
    "hot": "22068963",
    "url": "https://www.toutiao.com/trending/7623614387089784851/?category_name=topic_innerflow&event_type=hot_board&log_pb=%7B%22category_name%22%3A%22topic_innerflow%22%2C%22cluster_type%22%3A%2212%22%2C%22enter_from%22%3A%22click_category%22%2C%22entrance_hotspot%22%3A%22outside%22%2C%22event_type%22%3A%22hot_board%22%2C%22hot_board_cluster_id%22%3A%227623614387089784851%22%2C%22hot_board_impr_id%22%3A%222026040213525126322A75551B0053726F%22%2C%22jump_page%22%3A%22hot_board_page%22%2C%22location%22%3A%22news_hot_card%22%2C%22page_location%22%3A%22hot_board_page%22%2C%22source%22%3A%22trending_tab%22%2C%22style_id%22%3A%2240132%22%2C%22title%22%3A%22%E5%8E%BF%E5%A7%94%E4%B9%A6%E8%AE%B0%E2%80%9C%E5%85%AD%E7%A7%92%E8%87%B4%E8%BE%9E%E2%80%9D%E7%81%AB%E4%BA%86%22%7D&rank=&style_id=40132&topic_id=7623614387089784851",
    "time": ""
  },
  {
    "title": "中国国民党主席再度访陆“台独”破防",
    "hot": "19968824",
    "url": "https://www.toutiao.com/trending/7622910939541258303/?category_name=topic_innerflow&event_type=hot_board&log_pb=%7B%22category_name%22%3A%22topic_innerflow%22%2C%22cluster_type%22%3A%222%22%2C%22enter_from%22%3A%22click_category%22%2C%22entrance_hotspot%22%3A%22outside%22%2C%22event_type%22%3A%22hot_board%22%2C%22hot_board_cluster_id%22%3A%227622910939541258303%22%2C%22hot_board_impr_id%22%3A%222026040213525126322A75551B0053726F%22%2C%22jump_page%22%3A%22hot_board_page%22%2C%22location%22%3A%22news_hot_card%22%2C%22page_location%22%3A%22hot_board_page%22%2C%22source%22%3A%22trending_tab%22%2C%22style_id%22%3A%2240132%22%2C%22title%22%3A%22%E4%B8%AD%E5%9B%BD%E5%9B%BD%E6%B0%91%E5%85%9A%E4%B8%BB%E5%B8%AD%E5%86%8D%E5%BA%A6%E8%AE%BF%E9%99%86%E2%80%9C%E5%8F%B0%E7%8B%AC%E2%80%9D%E7%A0%B4%E9%98%B2%22%7D&rank=&style_id=40132&topic_id=7622910939541258303",
    "time": ""
  },
  {
    "title": "勾结男团司机售卖艺人隐私3人被抓",
    "hot": "18068539",
    "url": "https://www.toutiao.com/trending/7623632292754079787/?category_name=topic_innerflow&event_type=hot_board&log_pb=%7B%22category_name%22%3A%22topic_innerflow%22%2C%22cluster_type%22%3A%222%22%2C%22enter_from%22%3A%22click_category%22%2C%22entrance_hotspot%22%3A%22outside%22%2C%22event_type%22%3A%22hot_board%22%2C%22hot_board_cluster_id%22%3A%227623632292754079787%22%2C%22hot_board_impr_id%22%3A%222026040213525126322A75551B0053726F%22%2C%22jump_page%22%3A%22hot_board_page%22%2C%22location%22%3A%22news_hot_card%22%2C%22page_location%22%3A%22hot_board_page%22%2C%22source%22%3A%22trending_tab%22%2C%22style_id%22%3A%2240132%22%2C%22title%22%3A%22%E5%8B%BE%E7%BB%93%E7%94%B7%E5%9B%A2%E5%8F%B8%E6%9C%BA%E5%94%AE%E5%8D%96%E8%89%BA%E4%BA%BA%E9%9A%90%E7%A7%813%E4%BA%BA%E8%A2%AB%E6%8A%93%22%7D&rank=&style_id=40132&topic_id=7623632292754079787",
    "time": ""
  },
  {
    "title": "特朗普话音刚落 伊朗导弹直扑以色列",
    "hot": "16349090",
    "url": "https://www.toutiao.com/trending/7623977327684226579/?category_name=topic_innerflow&event_type=hot_board&log_pb=%7B%22category_name%22%3A%22topic_innerflow%22%2C%22cluster_type%22%3A%225%22%2C%22enter_from%22%3A%22click_category%22%2C%22entrance_hotspot%22%3A%22outside%22%2C%22event_type%22%3A%22hot_board%22%2C%22hot_board_cluster_id%22%3A%227623977327684226579%22%2C%22hot_board_impr_id%22%3A%222026040213525126322A75551B0053726F%22%2C%22jump_page%22%3A%22hot_board_page%22%2C%22location%22%3A%22news_hot_card%22%2C%22page_location%22%3A%22hot_board_page%22%2C%22source%22%3A%22trending_tab%22%2C%22style_id%22%3A%2240132%22%2C%22title%22%3A%22%E7%89%B9%E6%9C%97%E6%99%AE%E8%AF%9D%E9%9F%B3%E5%88%9A%E8%90%BD+%E4%BC%8A%E6%9C%97%E5%AF%BC%E5%BC%B9%E7%9B%B4%E6%89%91%E4%BB%A5%E8%89%B2%E5%88%97%22%7D&rank=&style_id=40132&topic_id=7623977327684226579",
    "time": ""
  },
  {
    "title": "夫妻出卖5名亲生子女获利47万被判刑",
    "hot": "14793268",
    "url": "https://www.toutiao.com/trending/7623976202130735110/?category_name=topic_innerflow&event_type=hot_board&log_pb=%7B%22category_name%22%3A%22topic_innerflow%22%2C%22cluster_type%22%3A%226%22%2C%22enter_from%22%3A%22click_category%22%2C%22entrance_hotspot%22%3A%22outside%22%2C%22event_type%22%3A%22hot_board%22%2C%22hot_board_cluster_id%22%3A%227623976202130735110%22%2C%22hot_board_impr_id%22%3A%222026040213525126322A75551B0053726F%22%2C%22jump_page%22%3A%22hot_board_page%22%2C%22location%22%3A%22news_hot_card%22%2C%22page_location%22%3A%22hot_board_page%22%2C%22source%22%3A%22trending_tab%22%2C%22style_id%22%3A%2240132%22%2C%22title%22%3A%22%E5%A4%AB%E5%A6%BB%E5%87%BA%E5%8D%965%E5%90%8D%E4%BA%B2%E7%94%9F%E5%AD%90%E5%A5%B3%E8%8E%B7%E5%88%A947%E4%B8%87%E8%A2%AB%E5%88%A4%E5%88%91%22%7D&rank=&style_id=40132&topic_id=7623976202130735110",
    "time": ""
  },
  {
    "title": "三亚一海滩露出锋利钢筋",
    "hot": "13385503",
    "url": "https://www.toutiao.com/trending/7623542435922132998/?category_name=topic_innerflow&event_type=hot_board&log_pb=%7B%22category_name%22%3A%22topic_innerflow%22%2C%22cluster_type%22%3A%226%22%2C%22enter_from%22%3A%22click_category%22%2C%22entrance_hotspot%22%3A%22outside%22%2C%22event_type%22%3A%22hot_board%22%2C%22hot_board_cluster_id%22%3A%227623542435922132998%22%2C%22hot_board_impr_id%22%3A%222026040213525126322A75551B0053726F%22%2C%22jump_page%22%3A%22hot_board_page%22%2C%22location%22%3A%22news_hot_card%22%2C%22page_location%22%3A%22hot_board_page%22%2C%22source%22%3A%22trending_tab%22%2C%22style_id%22%3A%2240132%22%2C%22title%22%3A%22%E4%B8%89%E4%BA%9A%E4%B8%80%E6%B5%B7%E6%BB%A9%E9%9C%B2%E5%87%BA%E9%94%8B%E5%88%A9%E9%92%A2%E7%AD%8B%22%7D&rank=&style_id=40132&topic_id=7623542435922132998",
    "time": ""
  },
  {
    "title": "江西通报一医院解聘全体职工",
    "hot": "12111704",
    "url": "https://www.toutiao.com/trending/7623826241108574262/?category_name=topic_innerflow&event_type=hot_board&log_pb=%7B%22category_name%22%3A%22topic_innerflow%22%2C%22cluster_type%22%3A%222%22%2C%22enter_from%22%3A%22click_category%22%2C%22entrance_hotspot%22%3A%22outside%22%2C%22event_type%22%3A%22hot_board%22%2C%22hot_board_cluster_id%22%3A%227623826241108574262%22%2C%22hot_board_impr_id%22%3A%222026040213525126322A75551B0053726F%22%2C%22jump_page%22%3A%22hot_board_page%22%2C%22location%22%3A%22news_hot_card%22%2C%22page_location%22%3A%22hot_board_page%22%2C%22source%22%3A%22trending_tab%22%2C%22style_id%22%3A%2240132%22%2C%22title%22%3A%22%E6%B1%9F%E8%A5%BF%E9%80%9A%E6%8A%A5%E4%B8%80%E5%8C%BB%E9%99%A2%E8%A7%A3%E8%81%98%E5%85%A8%E4%BD%93%E8%81%8C%E5%B7%A5%22%7D&rank=&style_id=40132&topic_id=7623826241108574262",
    "time": ""
  }
]